supermarktconnector/__init__.py
supermarktconnector/ah.py
supermarktconnector/errors.py
supermarktconnector/jumbo.py
supermarktconnector-0.8.1.dist-info/LICENSE
supermarktconnector-0.8.1.dist-info/METADATA
supermarktconnector-0.8.1.dist-info/WHEEL
supermarktconnector-0.8.1.dist-info/top_level.txt
supermarktconnector-0.8.1.dist-info/RECORD
