Metadata-Version: 2.1
Name: supermarktconnector
Version: 0.8.1
Summary: Collecting product information from Dutch supermarkets: Albert Heijn and Jumbo
Home-page: https://github.com/bartmachielsen/SupermarktConnector
Author: Bart Machielsen
Author-email: bartmachielsen@gmail.com
License: UNKNOWN
Platform: UNKNOWN
Classifier: Programming Language :: Python :: 3
Classifier: License :: OSI Approved :: MIT License
Classifier: Operating System :: OS Independent
Requires-Dist: requests
